django_internationalization/__init__.py
django_internationalization/admin.py
django_internationalization/apps.py
django_internationalization/config.py
django_internationalization/forms.py
django_internationalization/models.py
django_internationalization/tests.py
django_internationalization/urls.py
django_internationalization/utilities.py
django_internationalization/views.py
django_internationalization/locale/__init__.py
django_internationalization/management/__init__.py
django_internationalization/management/commands/__init__.py
django_internationalization/management/commands/activate-all-languages.py
django_internationalization/management/commands/deactivate-all-languages.py
django_internationalization/management/commands/deploy-translation-module.py
django_internationalization/migrations/__init__.py
django_internationalization/templatetags/__init__.py
django_internationalization/templatetags/add_str.py
django_internationalization/templatetags/index.py
django_internationalization-1.3.dist-info/LICENSE
django_internationalization-1.3.dist-info/METADATA
django_internationalization-1.3.dist-info/WHEEL
django_internationalization-1.3.dist-info/entry_points.txt
django_internationalization-1.3.dist-info/top_level.txt
django_internationalization-1.3.dist-info/RECORD
