Metadata-Version: 2.1
Name: django-internationalization
Version: 1.3
Summary: UNKNOWN
Home-page: UNKNOWN
License: UNKNOWN
Platform: UNKNOWN
License-File: LICENSE
Requires-Dist: setuptools >=69.5.1
Requires-Dist: Django >=5.0.4
Requires-Dist: numpy >=1.26.4
Requires-Dist: openpyxl >=3.1.2
Requires-Dist: pandas >=2.2.2
Requires-Dist: polib >=1.2.0
Requires-Dist: XlsxWriter >=3.2.0
Requires-Dist: xlwt >=1.3.0
